{
    "exercise_id": "ז_9_25",
    "section_id": 1,
    "section_number": "א",
    "type": "solution_3",
    "text": "    * **O(0,0)**\n    * **B(-4,0)** (כי $BO=4$ ו-B על ציר X שלילי).\n    * **E(0, $y_E$):** נתון $EC=4$. אם C(x_C, y_C), ו-E על ציר ה-y, אז $|x_C|=4$. מתוך האיור $x_C=4$. לכן, **C(4, $y_C$)**.\n    * **D:** נתון $y_D = 2$. הקטע DC מקביל לציר ה-x, ולכן $y_D = y_C = 2$. כלומר, $C(4,2)$. אז $D(x_D, 2)$. מתוך האיור, D נמצאת משמאל לציר ה-y. נתון $FC = 2DF$. F היא אמצע AB. שיעורי A לא ידועים עדיין.\n\n    * נחזור לנקודה E. אם $EC=4$ ו-$C(4,2)$, ו-E על ציר ה-y, אז E היא $E(0, y_C)$. לכן $E(0,2)$. (המרחק בין (0,2) ל-(4,2) הוא 4 יחידות, וזה מסתדר עם $EC=4$).\n\n    * **P:** נתון $CP=4$. הקטע CP מקביל לציר ה-y. אם $C(4,2)$, אז $P(x_C, y_P)$. $x_P = x_C = 4$. מרחק אנכי 4 יחידות מ-C(4,2) כלפי מטה (מהאיור). לכן $y_P = y_C - 4 = 2 - 4 = -2$. לכן **P(4,-2)**.\n\n    * **A:** AH מקביל לציר ה-y. אז $x_A = x_H$. F היא אמצע AB. $B(-4,0)$. $y_D=2$. מהאיור, A נמצאת מעל D ו-F היא ביניהם. מתוך האיור $x_F = 0$. אם F היא אמצע AB, אז $x_F = \\frac{x_A+x_B}{2} = \\frac{x_A + (-4)}{2} = 0$. מכאן $x_A - 4 = 0$, כלומר $x_A = 4$. אבל מהאיור A נמצאת משמאל לציר ה-y. יש סתירה. השרטוט והנתונים לא תמיד תואמים. נניח שהשרטוט מדויק יותר ביחסים בין הנקודות.\n\n    **בואו ננסה גישה אחרת, מהשרטוט עצמו:**"
}